ai_fuzzer/__init__.py
ai_fuzzer/cli.py
ai_fuzzer/geminis/run.py
ai_fuzzer/geminis/fetch/__init__.py
ai_fuzzer/geminis/fetch/fetch_docs.py
ai_fuzzer/geminis/llm/__init__.py
ai_fuzzer/geminis/llm/gem_request.py
ai_fuzzer/geminis/logger/__init__.py
ai_fuzzer/geminis/logger/logs.py
ai_fuzzer/geminis/parsing/__init__.py
ai_fuzzer/geminis/parsing/function_parser.py
ai_fuzzer/geminis/sandbox/__init__.py
ai_fuzzer/geminis/sandbox/sandbox.py
ai_fuzzer/geminis/smell/__init__.py
ai_fuzzer/geminis/smell/smell.py
geminis-0.1.48.dist-info/licenses/LICENSE
geminis-0.1.48.dist-info/METADATA
geminis-0.1.48.dist-info/WHEEL
geminis-0.1.48.dist-info/entry_points.txt
geminis-0.1.48.dist-info/top_level.txt
geminis-0.1.48.dist-info/RECORD
