Metadata-Version: 2.4
Name: Geminis
Version: 0.1.48
Summary: AI-powered Python fuzzer using Gemini and Atheris to automatically generate and execute fuzzing harnesses.
Author-email: Mario Marku <mariomarku7@gmail.com>
License-Expression: GPL-3.0-or-later
Project-URL: Homepage, https://github.com/mariobx
Project-URL: Repository, https://github.com/mariobx/Geminis
Requires-Python: <3.12,>=3.11
License-File: LICENSE
Requires-Dist: google-genai>=0.3.2
Requires-Dist: pyyaml>=6.0
Requires-Dist: atheris==2.3.0
Requires-Dist: path==17.1.0
Requires-Dist: radon>=5.0.0
Dynamic: license-file
